{
    "value":  [
                  {
                      "id":  1209515716,
                      "node_id":  "R_kgDOSBe-xA",
                      "name":  "Linklyt",
                      "full_name":  "AbhiGuru25/Linklyt",
                      "private":  false,
                      "owner":  {
                                    "login":  "AbhiGuru25",
                                    "id":  162453908,
                                    "node_id":  "U_kgDOCa7ZlA",
                                    "avatar_url":  "https://avatars.githubusercontent.com/u/162453908?v=4",
                                    "gravatar_id":  "",
                                    "url":  "https://api.github.com/users/AbhiGuru25",
                                    "html_url":  "https://github.com/AbhiGuru25",
                                    "followers_url":  "https://api.github.com/users/AbhiGuru25/followers",
                                    "following_url":  "https://api.github.com/users/AbhiGuru25/following{/other_user}",
                                    "gists_url":  "https://api.github.com/users/AbhiGuru25/gists{/gist_id}",
                                    "starred_url":  "https://api.github.com/users/AbhiGuru25/starred{/owner}{/repo}",
                                    "subscriptions_url":  "https://api.github.com/users/AbhiGuru25/subscriptions",
                                    "organizations_url":  "https://api.github.com/users/AbhiGuru25/orgs",
                                    "repos_url":  "https://api.github.com/users/AbhiGuru25/repos",
                                    "events_url":  "https://api.github.com/users/AbhiGuru25/events{/privacy}",
                                    "received_events_url":  "https://api.github.com/users/AbhiGuru25/received_events",
                                    "type":  "User",
                                    "user_view_type":  "public",
                                    "site_admin":  false
                                },
                      "html_url":  "https://github.com/AbhiGuru25/Linklyt",
                      "description":  null,
                      "fork":  false,
                      "url":  "https://api.github.com/repos/AbhiGuru25/Linklyt",
                      "forks_url":  "https://api.github.com/repos/AbhiGuru25/Linklyt/forks",
                      "keys_url":  "https://api.github.com/repos/AbhiGuru25/Linklyt/keys{/key_id}",
                      "collaborators_url":  "https://api.github.com/repos/AbhiGuru25/Linklyt/collaborators{/collaborator}",
                      "teams_url":  "https://api.github.com/repos/AbhiGuru25/Linklyt/teams",
                      "hooks_url":  "https://api.github.com/repos/AbhiGuru25/Linklyt/hooks",
                      "issue_events_url":  "https://api.github.com/repos/AbhiGuru25/Linklyt/issues/events{/number}",
                      "events_url":  "https://api.github.com/repos/AbhiGuru25/Linklyt/events",
                      "assignees_url":  "https://api.github.com/repos/AbhiGuru25/Linklyt/assignees{/user}",
                      "branches_url":  "https://api.github.com/repos/AbhiGuru25/Linklyt/branches{/branch}",
                      "tags_url":  "https://api.github.com/repos/AbhiGuru25/Linklyt/tags",
                      "blobs_url":  "https://api.github.com/repos/AbhiGuru25/Linklyt/git/blobs{/sha}",
                      "git_tags_url":  "https://api.github.com/repos/AbhiGuru25/Linklyt/git/tags{/sha}",
                      "git_refs_url":  "https://api.github.com/repos/AbhiGuru25/Linklyt/git/refs{/sha}",
                      "trees_url":  "https://api.github.com/repos/AbhiGuru25/Linklyt/git/trees{/sha}",
                      "statuses_url":  "https://api.github.com/repos/AbhiGuru25/Linklyt/statuses/{sha}",
                      "languages_url":  "https://api.github.com/repos/AbhiGuru25/Linklyt/languages",
                      "stargazers_url":  "https://api.github.com/repos/AbhiGuru25/Linklyt/stargazers",
                      "contributors_url":  "https://api.github.com/repos/AbhiGuru25/Linklyt/contributors",
                      "subscribers_url":  "https://api.github.com/repos/AbhiGuru25/Linklyt/subscribers",
                      "subscription_url":  "https://api.github.com/repos/AbhiGuru25/Linklyt/subscription",
                      "commits_url":  "https://api.github.com/repos/AbhiGuru25/Linklyt/commits{/sha}",
                      "git_commits_url":  "https://api.github.com/repos/AbhiGuru25/Linklyt/git/commits{/sha}",
                      "comments_url":  "https://api.github.com/repos/AbhiGuru25/Linklyt/comments{/number}",
                      "issue_comment_url":  "https://api.github.com/repos/AbhiGuru25/Linklyt/issues/comments{/number}",
                      "contents_url":  "https://api.github.com/repos/AbhiGuru25/Linklyt/contents/{+path}",
                      "compare_url":  "https://api.github.com/repos/AbhiGuru25/Linklyt/compare/{base}...{head}",
                      "merges_url":  "https://api.github.com/repos/AbhiGuru25/Linklyt/merges",
                      "archive_url":  "https://api.github.com/repos/AbhiGuru25/Linklyt/{archive_format}{/ref}",
                      "downloads_url":  "https://api.github.com/repos/AbhiGuru25/Linklyt/downloads",
                      "issues_url":  "https://api.github.com/repos/AbhiGuru25/Linklyt/issues{/number}",
                      "pulls_url":  "https://api.github.com/repos/AbhiGuru25/Linklyt/pulls{/number}",
                      "milestones_url":  "https://api.github.com/repos/AbhiGuru25/Linklyt/milestones{/number}",
                      "notifications_url":  "https://api.github.com/repos/AbhiGuru25/Linklyt/notifications{?since,all,participating}",
                      "labels_url":  "https://api.github.com/repos/AbhiGuru25/Linklyt/labels{/name}",
                      "releases_url":  "https://api.github.com/repos/AbhiGuru25/Linklyt/releases{/id}",
                      "deployments_url":  "https://api.github.com/repos/AbhiGuru25/Linklyt/deployments",
                      "created_at":  "2026-04-13T14:01:35Z",
                      "updated_at":  "2026-04-28T19:41:40Z",
                      "pushed_at":  "2026-04-28T19:41:36Z",
                      "git_url":  "git://github.com/AbhiGuru25/Linklyt.git",
                      "ssh_url":  "git@github.com:AbhiGuru25/Linklyt.git",
                      "clone_url":  "https://github.com/AbhiGuru25/Linklyt.git",
                      "svn_url":  "https://github.com/AbhiGuru25/Linklyt",
                      "homepage":  "https://linklyt-tau.vercel.app",
                      "size":  650,
                      "stargazers_count":  0,
                      "watchers_count":  0,
                      "language":  "JavaScript",
                      "has_issues":  true,
                      "has_projects":  true,
                      "has_downloads":  true,
                      "has_wiki":  true,
                      "has_pages":  false,
                      "has_discussions":  false,
                      "forks_count":  0,
                      "mirror_url":  null,
                      "archived":  false,
                      "disabled":  false,
                      "open_issues_count":  0,
                      "license":  null,
                      "allow_forking":  true,
                      "is_template":  false,
                      "web_commit_signoff_required":  false,
                      "has_pull_requests":  true,
                      "pull_request_creation_policy":  "all",
                      "topics":  [

                                 ],
                      "visibility":  "public",
                      "forks":  0,
                      "open_issues":  0,
                      "watchers":  0,
                      "default_branch":  "main"
                  },
                  {
                      "id":  1210718328,
                      "node_id":  "R_kgDOSCoYeA",
                      "name":  "RAPOS",
                      "full_name":  "AbhiGuru25/RAPOS",
                      "private":  false,
                      "owner":  {
                                    "login":  "AbhiGuru25",
                                    "id":  162453908,
                                    "node_id":  "U_kgDOCa7ZlA",
                                    "avatar_url":  "https://avatars.githubusercontent.com/u/162453908?v=4",
                                    "gravatar_id":  "",
                                    "url":  "https://api.github.com/users/AbhiGuru25",
                                    "html_url":  "https://github.com/AbhiGuru25",
                                    "followers_url":  "https://api.github.com/users/AbhiGuru25/followers",
                                    "following_url":  "https://api.github.com/users/AbhiGuru25/following{/other_user}",
                                    "gists_url":  "https://api.github.com/users/AbhiGuru25/gists{/gist_id}",
                                    "starred_url":  "https://api.github.com/users/AbhiGuru25/starred{/owner}{/repo}",
                                    "subscriptions_url":  "https://api.github.com/users/AbhiGuru25/subscriptions",
                                    "organizations_url":  "https://api.github.com/users/AbhiGuru25/orgs",
                                    "repos_url":  "https://api.github.com/users/AbhiGuru25/repos",
                                    "events_url":  "https://api.github.com/users/AbhiGuru25/events{/privacy}",
                                    "received_events_url":  "https://api.github.com/users/AbhiGuru25/received_events",
                                    "type":  "User",
                                    "user_view_type":  "public",
                                    "site_admin":  false
                                },
                      "html_url":  "https://github.com/AbhiGuru25/RAPOS",
                      "description":  null,
                      "fork":  false,
                      "url":  "https://api.github.com/repos/AbhiGuru25/RAPOS",
                      "forks_url":  "https://api.github.com/repos/AbhiGuru25/RAPOS/forks",
                      "keys_url":  "https://api.github.com/repos/AbhiGuru25/RAPOS/keys{/key_id}",
                      "collaborators_url":  "https://api.github.com/repos/AbhiGuru25/RAPOS/collaborators{/collaborator}",
                      "teams_url":  "https://api.github.com/repos/AbhiGuru25/RAPOS/teams",
                      "hooks_url":  "https://api.github.com/repos/AbhiGuru25/RAPOS/hooks",
                      "issue_events_url":  "https://api.github.com/repos/AbhiGuru25/RAPOS/issues/events{/number}",
                      "events_url":  "https://api.github.com/repos/AbhiGuru25/RAPOS/events",
                      "assignees_url":  "https://api.github.com/repos/AbhiGuru25/RAPOS/assignees{/user}",
                      "branches_url":  "https://api.github.com/repos/AbhiGuru25/RAPOS/branches{/branch}",
                      "tags_url":  "https://api.github.com/repos/AbhiGuru25/RAPOS/tags",
                      "blobs_url":  "https://api.github.com/repos/AbhiGuru25/RAPOS/git/blobs{/sha}",
                      "git_tags_url":  "https://api.github.com/repos/AbhiGuru25/RAPOS/git/tags{/sha}",
                      "git_refs_url":  "https://api.github.com/repos/AbhiGuru25/RAPOS/git/refs{/sha}",
                      "trees_url":  "https://api.github.com/repos/AbhiGuru25/RAPOS/git/trees{/sha}",
                      "statuses_url":  "https://api.github.com/repos/AbhiGuru25/RAPOS/statuses/{sha}",
                      "languages_url":  "https://api.github.com/repos/AbhiGuru25/RAPOS/languages",
                      "stargazers_url":  "https://api.github.com/repos/AbhiGuru25/RAPOS/stargazers",
                      "contributors_url":  "https://api.github.com/repos/AbhiGuru25/RAPOS/contributors",
                      "subscribers_url":  "https://api.github.com/repos/AbhiGuru25/RAPOS/subscribers",
                      "subscription_url":  "https://api.github.com/repos/AbhiGuru25/RAPOS/subscription",
                      "commits_url":  "https://api.github.com/repos/AbhiGuru25/RAPOS/commits{/sha}",
                      "git_commits_url":  "https://api.github.com/repos/AbhiGuru25/RAPOS/git/commits{/sha}",
                      "comments_url":  "https://api.github.com/repos/AbhiGuru25/RAPOS/comments{/number}",
                      "issue_comment_url":  "https://api.github.com/repos/AbhiGuru25/RAPOS/issues/comments{/number}",
                      "contents_url":  "https://api.github.com/repos/AbhiGuru25/RAPOS/contents/{+path}",
                      "compare_url":  "https://api.github.com/repos/AbhiGuru25/RAPOS/compare/{base}...{head}",
                      "merges_url":  "https://api.github.com/repos/AbhiGuru25/RAPOS/merges",
                      "archive_url":  "https://api.github.com/repos/AbhiGuru25/RAPOS/{archive_format}{/ref}",
                      "downloads_url":  "https://api.github.com/repos/AbhiGuru25/RAPOS/downloads",
                      "issues_url":  "https://api.github.com/repos/AbhiGuru25/RAPOS/issues{/number}",
                      "pulls_url":  "https://api.github.com/repos/AbhiGuru25/RAPOS/pulls{/number}",
                      "milestones_url":  "https://api.github.com/repos/AbhiGuru25/RAPOS/milestones{/number}",
                      "notifications_url":  "https://api.github.com/repos/AbhiGuru25/RAPOS/notifications{?since,all,participating}",
                      "labels_url":  "https://api.github.com/repos/AbhiGuru25/RAPOS/labels{/name}",
                      "releases_url":  "https://api.github.com/repos/AbhiGuru25/RAPOS/releases{/id}",
                      "deployments_url":  "https://api.github.com/repos/AbhiGuru25/RAPOS/deployments",
                      "created_at":  "2026-04-14T17:30:41Z",
                      "updated_at":  "2026-04-20T19:22:55Z",
                      "pushed_at":  "2026-04-20T19:22:51Z",
                      "git_url":  "git://github.com/AbhiGuru25/RAPOS.git",
                      "ssh_url":  "git@github.com:AbhiGuru25/RAPOS.git",
                      "clone_url":  "https://github.com/AbhiGuru25/RAPOS.git",
                      "svn_url":  "https://github.com/AbhiGuru25/RAPOS",
                      "homepage":  "https://rapos.vercel.app",
                      "size":  2550,
                      "stargazers_count":  0,
                      "watchers_count":  0,
                      "language":  "HTML",
                      "has_issues":  true,
                      "has_projects":  true,
                      "has_downloads":  true,
                      "has_wiki":  true,
                      "has_pages":  false,
                      "has_discussions":  false,
                      "forks_count":  0,
                      "mirror_url":  null,
                      "archived":  false,
                      "disabled":  false,
                      "open_issues_count":  0,
                      "license":  null,
                      "allow_forking":  true,
                      "is_template":  false,
                      "web_commit_signoff_required":  false,
                      "has_pull_requests":  true,
                      "pull_request_creation_policy":  "all",
                      "topics":  [

                                 ],
                      "visibility":  "public",
                      "forks":  0,
                      "open_issues":  0,
                      "watchers":  0,
                      "default_branch":  "main"
                  },
                  {
                      "id":  1180183490,
                      "node_id":  "R_kgDORlgrwg",
                      "name":  "Fraud-Detection",
                      "full_name":  "AbhiGuru25/Fraud-Detection",
                      "private":  false,
                      "owner":  {
                                    "login":  "AbhiGuru25",
                                    "id":  162453908,
                                    "node_id":  "U_kgDOCa7ZlA",
                                    "avatar_url":  "https://avatars.githubusercontent.com/u/162453908?v=4",
                                    "gravatar_id":  "",
                                    "url":  "https://api.github.com/users/AbhiGuru25",
                                    "html_url":  "https://github.com/AbhiGuru25",
                                    "followers_url":  "https://api.github.com/users/AbhiGuru25/followers",
                                    "following_url":  "https://api.github.com/users/AbhiGuru25/following{/other_user}",
                                    "gists_url":  "https://api.github.com/users/AbhiGuru25/gists{/gist_id}",
                                    "starred_url":  "https://api.github.com/users/AbhiGuru25/starred{/owner}{/repo}",
                                    "subscriptions_url":  "https://api.github.com/users/AbhiGuru25/subscriptions",
                                    "organizations_url":  "https://api.github.com/users/AbhiGuru25/orgs",
                                    "repos_url":  "https://api.github.com/users/AbhiGuru25/repos",
                                    "events_url":  "https://api.github.com/users/AbhiGuru25/events{/privacy}",
                                    "received_events_url":  "https://api.github.com/users/AbhiGuru25/received_events",
                                    "type":  "User",
                                    "user_view_type":  "public",
                                    "site_admin":  false
                                },
                      "html_url":  "https://github.com/AbhiGuru25/Fraud-Detection",
                      "description":  null,
                      "fork":  false,
                      "url":  "https://api.github.com/repos/AbhiGuru25/Fraud-Detection",
                      "forks_url":  "https://api.github.com/repos/AbhiGuru25/Fraud-Detection/forks",
                      "keys_url":  "https://api.github.com/repos/AbhiGuru25/Fraud-Detection/keys{/key_id}",
                      "collaborators_url":  "https://api.github.com/repos/AbhiGuru25/Fraud-Detection/collaborators{/collaborator}",
                      "teams_url":  "https://api.github.com/repos/AbhiGuru25/Fraud-Detection/teams",
                      "hooks_url":  "https://api.github.com/repos/AbhiGuru25/Fraud-Detection/hooks",
                      "issue_events_url":  "https://api.github.com/repos/AbhiGuru25/Fraud-Detection/issues/events{/number}",
                      "events_url":  "https://api.github.com/repos/AbhiGuru25/Fraud-Detection/events",
                      "assignees_url":  "https://api.github.com/repos/AbhiGuru25/Fraud-Detection/assignees{/user}",
                      "branches_url":  "https://api.github.com/repos/AbhiGuru25/Fraud-Detection/branches{/branch}",
                      "tags_url":  "https://api.github.com/repos/AbhiGuru25/Fraud-Detection/tags",
                      "blobs_url":  "https://api.github.com/repos/AbhiGuru25/Fraud-Detection/git/blobs{/sha}",
                      "git_tags_url":  "https://api.github.com/repos/AbhiGuru25/Fraud-Detection/git/tags{/sha}",
                      "git_refs_url":  "https://api.github.com/repos/AbhiGuru25/Fraud-Detection/git/refs{/sha}",
                      "trees_url":  "https://api.github.com/repos/AbhiGuru25/Fraud-Detection/git/trees{/sha}",
                      "statuses_url":  "https://api.github.com/repos/AbhiGuru25/Fraud-Detection/statuses/{sha}",
                      "languages_url":  "https://api.github.com/repos/AbhiGuru25/Fraud-Detection/languages",
                      "stargazers_url":  "https://api.github.com/repos/AbhiGuru25/Fraud-Detection/stargazers",
                      "contributors_url":  "https://api.github.com/repos/AbhiGuru25/Fraud-Detection/contributors",
                      "subscribers_url":  "https://api.github.com/repos/AbhiGuru25/Fraud-Detection/subscribers",
                      "subscription_url":  "https://api.github.com/repos/AbhiGuru25/Fraud-Detection/subscription",
                      "commits_url":  "https://api.github.com/repos/AbhiGuru25/Fraud-Detection/commits{/sha}",
                      "git_commits_url":  "https://api.github.com/repos/AbhiGuru25/Fraud-Detection/git/commits{/sha}",
                      "comments_url":  "https://api.github.com/repos/AbhiGuru25/Fraud-Detection/comments{/number}",
                      "issue_comment_url":  "https://api.github.com/repos/AbhiGuru25/Fraud-Detection/issues/comments{/number}",
                      "contents_url":  "https://api.github.com/repos/AbhiGuru25/Fraud-Detection/contents/{+path}",
                      "compare_url":  "https://api.github.com/repos/AbhiGuru25/Fraud-Detection/compare/{base}...{head}",
                      "merges_url":  "https://api.github.com/repos/AbhiGuru25/Fraud-Detection/merges",
                      "archive_url":  "https://api.github.com/repos/AbhiGuru25/Fraud-Detection/{archive_format}{/ref}",
                      "downloads_url":  "https://api.github.com/repos/AbhiGuru25/Fraud-Detection/downloads",
                      "issues_url":  "https://api.github.com/repos/AbhiGuru25/Fraud-Detection/issues{/number}",
                      "pulls_url":  "https://api.github.com/repos/AbhiGuru25/Fraud-Detection/pulls{/number}",
                      "milestones_url":  "https://api.github.com/repos/AbhiGuru25/Fraud-Detection/milestones{/number}",
                      "notifications_url":  "https://api.github.com/repos/AbhiGuru25/Fraud-Detection/notifications{?since,all,participating}",
                      "labels_url":  "https://api.github.com/repos/AbhiGuru25/Fraud-Detection/labels{/name}",
                      "releases_url":  "https://api.github.com/repos/AbhiGuru25/Fraud-Detection/releases{/id}",
                      "deployments_url":  "https://api.github.com/repos/AbhiGuru25/Fraud-Detection/deployments",
                      "created_at":  "2026-03-12T19:36:17Z",
                      "updated_at":  "2026-03-27T11:32:53Z",
                      "pushed_at":  "2026-03-27T11:32:50Z",
                      "git_url":  "git://github.com/AbhiGuru25/Fraud-Detection.git",
                      "ssh_url":  "git@github.com:AbhiGuru25/Fraud-Detection.git",
                      "clone_url":  "https://github.com/AbhiGuru25/Fraud-Detection.git",
                      "svn_url":  "https://github.com/AbhiGuru25/Fraud-Detection",
                      "homepage":  null,
                      "size":  61791,
                      "stargazers_count":  0,
                      "watchers_count":  0,
                      "language":  "Python",
                      "has_issues":  true,
                      "has_projects":  true,
                      "has_downloads":  true,
                      "has_wiki":  true,
                      "has_pages":  false,
                      "has_discussions":  false,
                      "forks_count":  0,
                      "mirror_url":  null,
                      "archived":  false,
                      "disabled":  false,
                      "open_issues_count":  0,
                      "license":  null,
                      "allow_forking":  true,
                      "is_template":  false,
                      "web_commit_signoff_required":  false,
                      "has_pull_requests":  true,
                      "pull_request_creation_policy":  "all",
                      "topics":  [

                                 ],
                      "visibility":  "public",
                      "forks":  0,
                      "open_issues":  0,
                      "watchers":  0,
                      "default_branch":  "main"
                  },
                  {
                      "id":  1180183826,
                      "node_id":  "R_kgDORlgtEg",
                      "name":  "Liver-Cirrhosis-Detection",
                      "full_name":  "AbhiGuru25/Liver-Cirrhosis-Detection",
                      "private":  false,
                      "owner":  {
                                    "login":  "AbhiGuru25",
                                    "id":  162453908,
                                    "node_id":  "U_kgDOCa7ZlA",
                                    "avatar_url":  "https://avatars.githubusercontent.com/u/162453908?v=4",
                                    "gravatar_id":  "",
                                    "url":  "https://api.github.com/users/AbhiGuru25",
                                    "html_url":  "https://github.com/AbhiGuru25",
                                    "followers_url":  "https://api.github.com/users/AbhiGuru25/followers",
                                    "following_url":  "https://api.github.com/users/AbhiGuru25/following{/other_user}",
                                    "gists_url":  "https://api.github.com/users/AbhiGuru25/gists{/gist_id}",
                                    "starred_url":  "https://api.github.com/users/AbhiGuru25/starred{/owner}{/repo}",
                                    "subscriptions_url":  "https://api.github.com/users/AbhiGuru25/subscriptions",
                                    "organizations_url":  "https://api.github.com/users/AbhiGuru25/orgs",
                                    "repos_url":  "https://api.github.com/users/AbhiGuru25/repos",
                                    "events_url":  "https://api.github.com/users/AbhiGuru25/events{/privacy}",
                                    "received_events_url":  "https://api.github.com/users/AbhiGuru25/received_events",
                                    "type":  "User",
                                    "user_view_type":  "public",
                                    "site_admin":  false
                                },
                      "html_url":  "https://github.com/AbhiGuru25/Liver-Cirrhosis-Detection",
                      "description":  null,
                      "fork":  false,
                      "url":  "https://api.github.com/repos/AbhiGuru25/Liver-Cirrhosis-Detection",
                      "forks_url":  "https://api.github.com/repos/AbhiGuru25/Liver-Cirrhosis-Detection/forks",
                      "keys_url":  "https://api.github.com/repos/AbhiGuru25/Liver-Cirrhosis-Detection/keys{/key_id}",
                      "collaborators_url":  "https://api.github.com/repos/AbhiGuru25/Liver-Cirrhosis-Detection/collaborators{/collaborator}",
                      "teams_url":  "https://api.github.com/repos/AbhiGuru25/Liver-Cirrhosis-Detection/teams",
                      "hooks_url":  "https://api.github.com/repos/AbhiGuru25/Liver-Cirrhosis-Detection/hooks",
                      "issue_events_url":  "https://api.github.com/repos/AbhiGuru25/Liver-Cirrhosis-Detection/issues/events{/number}",
                      "events_url":  "https://api.github.com/repos/AbhiGuru25/Liver-Cirrhosis-Detection/events",
                      "assignees_url":  "https://api.github.com/repos/AbhiGuru25/Liver-Cirrhosis-Detection/assignees{/user}",
                      "branches_url":  "https://api.github.com/repos/AbhiGuru25/Liver-Cirrhosis-Detection/branches{/branch}",
                      "tags_url":  "https://api.github.com/repos/AbhiGuru25/Liver-Cirrhosis-Detection/tags",
                      "blobs_url":  "https://api.github.com/repos/AbhiGuru25/Liver-Cirrhosis-Detection/git/blobs{/sha}",
                      "git_tags_url":  "https://api.github.com/repos/AbhiGuru25/Liver-Cirrhosis-Detection/git/tags{/sha}",
                      "git_refs_url":  "https://api.github.com/repos/AbhiGuru25/Liver-Cirrhosis-Detection/git/refs{/sha}",
                      "trees_url":  "https://api.github.com/repos/AbhiGuru25/Liver-Cirrhosis-Detection/git/trees{/sha}",
                      "statuses_url":  "https://api.github.com/repos/AbhiGuru25/Liver-Cirrhosis-Detection/statuses/{sha}",
                      "languages_url":  "https://api.github.com/repos/AbhiGuru25/Liver-Cirrhosis-Detection/languages",
                      "stargazers_url":  "https://api.github.com/repos/AbhiGuru25/Liver-Cirrhosis-Detection/stargazers",
                      "contributors_url":  "https://api.github.com/repos/AbhiGuru25/Liver-Cirrhosis-Detection/contributors",
                      "subscribers_url":  "https://api.github.com/repos/AbhiGuru25/Liver-Cirrhosis-Detection/subscribers",
                      "subscription_url":  "https://api.github.com/repos/AbhiGuru25/Liver-Cirrhosis-Detection/subscription",
                      "commits_url":  "https://api.github.com/repos/AbhiGuru25/Liver-Cirrhosis-Detection/commits{/sha}",
                      "git_commits_url":  "https://api.github.com/repos/AbhiGuru25/Liver-Cirrhosis-Detection/git/commits{/sha}",
                      "comments_url":  "https://api.github.com/repos/AbhiGuru25/Liver-Cirrhosis-Detection/comments{/number}",
                      "issue_comment_url":  "https://api.github.com/repos/AbhiGuru25/Liver-Cirrhosis-Detection/issues/comments{/number}",
                      "contents_url":  "https://api.github.com/repos/AbhiGuru25/Liver-Cirrhosis-Detection/contents/{+path}",
                      "compare_url":  "https://api.github.com/repos/AbhiGuru25/Liver-Cirrhosis-Detection/compare/{base}...{head}",
                      "merges_url":  "https://api.github.com/repos/AbhiGuru25/Liver-Cirrhosis-Detection/merges",
                      "archive_url":  "https://api.github.com/repos/AbhiGuru25/Liver-Cirrhosis-Detection/{archive_format}{/ref}",
                      "downloads_url":  "https://api.github.com/repos/AbhiGuru25/Liver-Cirrhosis-Detection/downloads",
                      "issues_url":  "https://api.github.com/repos/AbhiGuru25/Liver-Cirrhosis-Detection/issues{/number}",
                      "pulls_url":  "https://api.github.com/repos/AbhiGuru25/Liver-Cirrhosis-Detection/pulls{/number}",
                      "milestones_url":  "https://api.github.com/repos/AbhiGuru25/Liver-Cirrhosis-Detection/milestones{/number}",
                      "notifications_url":  "https://api.github.com/repos/AbhiGuru25/Liver-Cirrhosis-Detection/notifications{?since,all,participating}",
                      "labels_url":  "https://api.github.com/repos/AbhiGuru25/Liver-Cirrhosis-Detection/labels{/name}",
                      "releases_url":  "https://api.github.com/repos/AbhiGuru25/Liver-Cirrhosis-Detection/releases{/id}",
                      "deployments_url":  "https://api.github.com/repos/AbhiGuru25/Liver-Cirrhosis-Detection/deployments",
                      "created_at":  "2026-03-12T19:36:43Z",
                      "updated_at":  "2026-03-27T11:32:40Z",
                      "pushed_at":  "2026-03-27T11:32:36Z",
                      "git_url":  "git://github.com/AbhiGuru25/Liver-Cirrhosis-Detection.git",
                      "ssh_url":  "git@github.com:AbhiGuru25/Liver-Cirrhosis-Detection.git",
                      "clone_url":  "https://github.com/AbhiGuru25/Liver-Cirrhosis-Detection.git",
                      "svn_url":  "https://github.com/AbhiGuru25/Liver-Cirrhosis-Detection",
                      "homepage":  null,
                      "size":  9234,
                      "stargazers_count":  0,
                      "watchers_count":  0,
                      "language":  "Python",
                      "has_issues":  true,
                      "has_projects":  true,
                      "has_downloads":  true,
                      "has_wiki":  true,
                      "has_pages":  false,
                      "has_discussions":  false,
                      "forks_count":  0,
                      "mirror_url":  null,
                      "archived":  false,
                      "disabled":  false,
                      "open_issues_count":  0,
                      "license":  null,
                      "allow_forking":  true,
                      "is_template":  false,
                      "web_commit_signoff_required":  false,
                      "has_pull_requests":  true,
                      "pull_request_creation_policy":  "all",
                      "topics":  [

                                 ],
                      "visibility":  "public",
                      "forks":  0,
                      "open_issues":  0,
                      "watchers":  0,
                      "default_branch":  "main"
                  },
                  {
                      "id":  1180183229,
                      "node_id":  "R_kgDORlgqvQ",
                      "name":  "Forest-Cover-Prediction",
                      "full_name":  "AbhiGuru25/Forest-Cover-Prediction",
                      "private":  false,
                      "owner":  {
                                    "login":  "AbhiGuru25",
                                    "id":  162453908,
                                    "node_id":  "U_kgDOCa7ZlA",
                                    "avatar_url":  "https://avatars.githubusercontent.com/u/162453908?v=4",
                                    "gravatar_id":  "",
                                    "url":  "https://api.github.com/users/AbhiGuru25",
                                    "html_url":  "https://github.com/AbhiGuru25",
                                    "followers_url":  "https://api.github.com/users/AbhiGuru25/followers",
                                    "following_url":  "https://api.github.com/users/AbhiGuru25/following{/other_user}",
                                    "gists_url":  "https://api.github.com/users/AbhiGuru25/gists{/gist_id}",
                                    "starred_url":  "https://api.github.com/users/AbhiGuru25/starred{/owner}{/repo}",
                                    "subscriptions_url":  "https://api.github.com/users/AbhiGuru25/subscriptions",
                                    "organizations_url":  "https://api.github.com/users/AbhiGuru25/orgs",
                                    "repos_url":  "https://api.github.com/users/AbhiGuru25/repos",
                                    "events_url":  "https://api.github.com/users/AbhiGuru25/events{/privacy}",
                                    "received_events_url":  "https://api.github.com/users/AbhiGuru25/received_events",
                                    "type":  "User",
                                    "user_view_type":  "public",
                                    "site_admin":  false
                                },
                      "html_url":  "https://github.com/AbhiGuru25/Forest-Cover-Prediction",
                      "description":  null,
                      "fork":  false,
                      "url":  "https://api.github.com/repos/AbhiGuru25/Forest-Cover-Prediction",
                      "forks_url":  "https://api.github.com/repos/AbhiGuru25/Forest-Cover-Prediction/forks",
                      "keys_url":  "https://api.github.com/repos/AbhiGuru25/Forest-Cover-Prediction/keys{/key_id}",
                      "collaborators_url":  "https://api.github.com/repos/AbhiGuru25/Forest-Cover-Prediction/collaborators{/collaborator}",
                      "teams_url":  "https://api.github.com/repos/AbhiGuru25/Forest-Cover-Prediction/teams",
                      "hooks_url":  "https://api.github.com/repos/AbhiGuru25/Forest-Cover-Prediction/hooks",
                      "issue_events_url":  "https://api.github.com/repos/AbhiGuru25/Forest-Cover-Prediction/issues/events{/number}",
                      "events_url":  "https://api.github.com/repos/AbhiGuru25/Forest-Cover-Prediction/events",
                      "assignees_url":  "https://api.github.com/repos/AbhiGuru25/Forest-Cover-Prediction/assignees{/user}",
                      "branches_url":  "https://api.github.com/repos/AbhiGuru25/Forest-Cover-Prediction/branches{/branch}",
                      "tags_url":  "https://api.github.com/repos/AbhiGuru25/Forest-Cover-Prediction/tags",
                      "blobs_url":  "https://api.github.com/repos/AbhiGuru25/Forest-Cover-Prediction/git/blobs{/sha}",
                      "git_tags_url":  "https://api.github.com/repos/AbhiGuru25/Forest-Cover-Prediction/git/tags{/sha}",
                      "git_refs_url":  "https://api.github.com/repos/AbhiGuru25/Forest-Cover-Prediction/git/refs{/sha}",
                      "trees_url":  "https://api.github.com/repos/AbhiGuru25/Forest-Cover-Prediction/git/trees{/sha}",
                      "statuses_url":  "https://api.github.com/repos/AbhiGuru25/Forest-Cover-Prediction/statuses/{sha}",
                      "languages_url":  "https://api.github.com/repos/AbhiGuru25/Forest-Cover-Prediction/languages",
                      "stargazers_url":  "https://api.github.com/repos/AbhiGuru25/Forest-Cover-Prediction/stargazers",
                      "contributors_url":  "https://api.github.com/repos/AbhiGuru25/Forest-Cover-Prediction/contributors",
                      "subscribers_url":  "https://api.github.com/repos/AbhiGuru25/Forest-Cover-Prediction/subscribers",
                      "subscription_url":  "https://api.github.com/repos/AbhiGuru25/Forest-Cover-Prediction/subscription",
                      "commits_url":  "https://api.github.com/repos/AbhiGuru25/Forest-Cover-Prediction/commits{/sha}",
                      "git_commits_url":  "https://api.github.com/repos/AbhiGuru25/Forest-Cover-Prediction/git/commits{/sha}",
                      "comments_url":  "https://api.github.com/repos/AbhiGuru25/Forest-Cover-Prediction/comments{/number}",
                      "issue_comment_url":  "https://api.github.com/repos/AbhiGuru25/Forest-Cover-Prediction/issues/comments{/number}",
                      "contents_url":  "https://api.github.com/repos/AbhiGuru25/Forest-Cover-Prediction/contents/{+path}",
                      "compare_url":  "https://api.github.com/repos/AbhiGuru25/Forest-Cover-Prediction/compare/{base}...{head}",
                      "merges_url":  "https://api.github.com/repos/AbhiGuru25/Forest-Cover-Prediction/merges",
                      "archive_url":  "https://api.github.com/repos/AbhiGuru25/Forest-Cover-Prediction/{archive_format}{/ref}",
                      "downloads_url":  "https://api.github.com/repos/AbhiGuru25/Forest-Cover-Prediction/downloads",
                      "issues_url":  "https://api.github.com/repos/AbhiGuru25/Forest-Cover-Prediction/issues{/number}",
                      "pulls_url":  "https://api.github.com/repos/AbhiGuru25/Forest-Cover-Prediction/pulls{/number}",
                      "milestones_url":  "https://api.github.com/repos/AbhiGuru25/Forest-Cover-Prediction/milestones{/number}",
                      "notifications_url":  "https://api.github.com/repos/AbhiGuru25/Forest-Cover-Prediction/notifications{?since,all,participating}",
                      "labels_url":  "https://api.github.com/repos/AbhiGuru25/Forest-Cover-Prediction/labels{/name}",
                      "releases_url":  "https://api.github.com/repos/AbhiGuru25/Forest-Cover-Prediction/releases{/id}",
                      "deployments_url":  "https://api.github.com/repos/AbhiGuru25/Forest-Cover-Prediction/deployments",
                      "created_at":  "2026-03-12T19:35:56Z",
                      "updated_at":  "2026-03-27T11:32:26Z",
                      "pushed_at":  "2026-03-27T11:32:23Z",
                      "git_url":  "git://github.com/AbhiGuru25/Forest-Cover-Prediction.git",
                      "ssh_url":  "git@github.com:AbhiGuru25/Forest-Cover-Prediction.git",
                      "clone_url":  "https://github.com/AbhiGuru25/Forest-Cover-Prediction.git",
                      "svn_url":  "https://github.com/AbhiGuru25/Forest-Cover-Prediction",
                      "homepage":  null,
                      "size":  7086,
                      "stargazers_count":  0,
                      "watchers_count":  0,
                      "language":  "Python",
                      "has_issues":  true,
                      "has_projects":  true,
                      "has_downloads":  true,
                      "has_wiki":  true,
                      "has_pages":  false,
                      "has_discussions":  false,
                      "forks_count":  0,
                      "mirror_url":  null,
                      "archived":  false,
                      "disabled":  false,
                      "open_issues_count":  0,
                      "license":  null,
                      "allow_forking":  true,
                      "is_template":  false,
                      "web_commit_signoff_required":  false,
                      "has_pull_requests":  true,
                      "pull_request_creation_policy":  "all",
                      "topics":  [

                                 ],
                      "visibility":  "public",
                      "forks":  0,
                      "open_issues":  0,
                      "watchers":  0,
                      "default_branch":  "main"
                  },
                  {
                      "id":  1180182634,
                      "node_id":  "R_kgDORlgoag",
                      "name":  "ASL-Detection",
                      "full_name":  "AbhiGuru25/ASL-Detection",
                      "private":  false,
                      "owner":  {
                                    "login":  "AbhiGuru25",
                                    "id":  162453908,
                                    "node_id":  "U_kgDOCa7ZlA",
                                    "avatar_url":  "https://avatars.githubusercontent.com/u/162453908?v=4",
                                    "gravatar_id":  "",
                                    "url":  "https://api.github.com/users/AbhiGuru25",
                                    "html_url":  "https://github.com/AbhiGuru25",
                                    "followers_url":  "https://api.github.com/users/AbhiGuru25/followers",
                                    "following_url":  "https://api.github.com/users/AbhiGuru25/following{/other_user}",
                                    "gists_url":  "https://api.github.com/users/AbhiGuru25/gists{/gist_id}",
                                    "starred_url":  "https://api.github.com/users/AbhiGuru25/starred{/owner}{/repo}",
                                    "subscriptions_url":  "https://api.github.com/users/AbhiGuru25/subscriptions",
                                    "organizations_url":  "https://api.github.com/users/AbhiGuru25/orgs",
                                    "repos_url":  "https://api.github.com/users/AbhiGuru25/repos",
                                    "events_url":  "https://api.github.com/users/AbhiGuru25/events{/privacy}",
                                    "received_events_url":  "https://api.github.com/users/AbhiGuru25/received_events",
                                    "type":  "User",
                                    "user_view_type":  "public",
                                    "site_admin":  false
                                },
                      "html_url":  "https://github.com/AbhiGuru25/ASL-Detection",
                      "description":  null,
                      "fork":  false,
                      "url":  "https://api.github.com/repos/AbhiGuru25/ASL-Detection",
                      "forks_url":  "https://api.github.com/repos/AbhiGuru25/ASL-Detection/forks",
                      "keys_url":  "https://api.github.com/repos/AbhiGuru25/ASL-Detection/keys{/key_id}",
                      "collaborators_url":  "https://api.github.com/repos/AbhiGuru25/ASL-Detection/collaborators{/collaborator}",
                      "teams_url":  "https://api.github.com/repos/AbhiGuru25/ASL-Detection/teams",
                      "hooks_url":  "https://api.github.com/repos/AbhiGuru25/ASL-Detection/hooks",
                      "issue_events_url":  "https://api.github.com/repos/AbhiGuru25/ASL-Detection/issues/events{/number}",
                      "events_url":  "https://api.github.com/repos/AbhiGuru25/ASL-Detection/events",
                      "assignees_url":  "https://api.github.com/repos/AbhiGuru25/ASL-Detection/assignees{/user}",
                      "branches_url":  "https://api.github.com/repos/AbhiGuru25/ASL-Detection/branches{/branch}",
                      "tags_url":  "https://api.github.com/repos/AbhiGuru25/ASL-Detection/tags",
                      "blobs_url":  "https://api.github.com/repos/AbhiGuru25/ASL-Detection/git/blobs{/sha}",
                      "git_tags_url":  "https://api.github.com/repos/AbhiGuru25/ASL-Detection/git/tags{/sha}",
                      "git_refs_url":  "https://api.github.com/repos/AbhiGuru25/ASL-Detection/git/refs{/sha}",
                      "trees_url":  "https://api.github.com/repos/AbhiGuru25/ASL-Detection/git/trees{/sha}",
                      "statuses_url":  "https://api.github.com/repos/AbhiGuru25/ASL-Detection/statuses/{sha}",
                      "languages_url":  "https://api.github.com/repos/AbhiGuru25/ASL-Detection/languages",
                      "stargazers_url":  "https://api.github.com/repos/AbhiGuru25/ASL-Detection/stargazers",
                      "contributors_url":  "https://api.github.com/repos/AbhiGuru25/ASL-Detection/contributors",
                      "subscribers_url":  "https://api.github.com/repos/AbhiGuru25/ASL-Detection/subscribers",
                      "subscription_url":  "https://api.github.com/repos/AbhiGuru25/ASL-Detection/subscription",
                      "commits_url":  "https://api.github.com/repos/AbhiGuru25/ASL-Detection/commits{/sha}",
                      "git_commits_url":  "https://api.github.com/repos/AbhiGuru25/ASL-Detection/git/commits{/sha}",
                      "comments_url":  "https://api.github.com/repos/AbhiGuru25/ASL-Detection/comments{/number}",
                      "issue_comment_url":  "https://api.github.com/repos/AbhiGuru25/ASL-Detection/issues/comments{/number}",
                      "contents_url":  "https://api.github.com/repos/AbhiGuru25/ASL-Detection/contents/{+path}",
                      "compare_url":  "https://api.github.com/repos/AbhiGuru25/ASL-Detection/compare/{base}...{head}",
                      "merges_url":  "https://api.github.com/repos/AbhiGuru25/ASL-Detection/merges",
                      "archive_url":  "https://api.github.com/repos/AbhiGuru25/ASL-Detection/{archive_format}{/ref}",
                      "downloads_url":  "https://api.github.com/repos/AbhiGuru25/ASL-Detection/downloads",
                      "issues_url":  "https://api.github.com/repos/AbhiGuru25/ASL-Detection/issues{/number}",
                      "pulls_url":  "https://api.github.com/repos/AbhiGuru25/ASL-Detection/pulls{/number}",
                      "milestones_url":  "https://api.github.com/repos/AbhiGuru25/ASL-Detection/milestones{/number}",
                      "notifications_url":  "https://api.github.com/repos/AbhiGuru25/ASL-Detection/notifications{?since,all,participating}",
                      "labels_url":  "https://api.github.com/repos/AbhiGuru25/ASL-Detection/labels{/name}",
                      "releases_url":  "https://api.github.com/repos/AbhiGuru25/ASL-Detection/releases{/id}",
                      "deployments_url":  "https://api.github.com/repos/AbhiGuru25/ASL-Detection/deployments",
                      "created_at":  "2026-03-12T19:35:04Z",
                      "updated_at":  "2026-03-27T11:32:18Z",
                      "pushed_at":  "2026-03-27T11:32:15Z",
                      "git_url":  "git://github.com/AbhiGuru25/ASL-Detection.git",
                      "ssh_url":  "git@github.com:AbhiGuru25/ASL-Detection.git",
                      "clone_url":  "https://github.com/AbhiGuru25/ASL-Detection.git",
                      "svn_url":  "https://github.com/AbhiGuru25/ASL-Detection",
                      "homepage":  null,
                      "size":  51,
                      "stargazers_count":  0,
                      "watchers_count":  0,
                      "language":  "Python",
                      "has_issues":  true,
                      "has_projects":  true,
                      "has_downloads":  true,
                      "has_wiki":  true,
                      "has_pages":  false,
                      "has_discussions":  false,
                      "forks_count":  0,
                      "mirror_url":  null,
                      "archived":  false,
                      "disabled":  false,
                      "open_issues_count":  0,
                      "license":  null,
                      "allow_forking":  true,
                      "is_template":  false,
                      "web_commit_signoff_required":  false,
                      "has_pull_requests":  true,
                      "pull_request_creation_policy":  "all",
                      "topics":  [

                                 ],
                      "visibility":  "public",
                      "forks":  0,
                      "open_issues":  0,
                      "watchers":  0,
                      "default_branch":  "main"
                  },
                  {
                      "id":  1180182926,
                      "node_id":  "R_kgDORlgpjg",
                      "name":  "Animal-Classification",
                      "full_name":  "AbhiGuru25/Animal-Classification",
                      "private":  false,
                      "owner":  {
                                    "login":  "AbhiGuru25",
                                    "id":  162453908,
                                    "node_id":  "U_kgDOCa7ZlA",
                                    "avatar_url":  "https://avatars.githubusercontent.com/u/162453908?v=4",
                                    "gravatar_id":  "",
                                    "url":  "https://api.github.com/users/AbhiGuru25",
                                    "html_url":  "https://github.com/AbhiGuru25",
                                    "followers_url":  "https://api.github.com/users/AbhiGuru25/followers",
                                    "following_url":  "https://api.github.com/users/AbhiGuru25/following{/other_user}",
                                    "gists_url":  "https://api.github.com/users/AbhiGuru25/gists{/gist_id}",
                                    "starred_url":  "https://api.github.com/users/AbhiGuru25/starred{/owner}{/repo}",
                                    "subscriptions_url":  "https://api.github.com/users/AbhiGuru25/subscriptions",
                                    "organizations_url":  "https://api.github.com/users/AbhiGuru25/orgs",
                                    "repos_url":  "https://api.github.com/users/AbhiGuru25/repos",
                                    "events_url":  "https://api.github.com/users/AbhiGuru25/events{/privacy}",
                                    "received_events_url":  "https://api.github.com/users/AbhiGuru25/received_events",
                                    "type":  "User",
                                    "user_view_type":  "public",
                                    "site_admin":  false
                                },
                      "html_url":  "https://github.com/AbhiGuru25/Animal-Classification",
                      "description":  null,
                      "fork":  false,
                      "url":  "https://api.github.com/repos/AbhiGuru25/Animal-Classification",
                      "forks_url":  "https://api.github.com/repos/AbhiGuru25/Animal-Classification/forks",
                      "keys_url":  "https://api.github.com/repos/AbhiGuru25/Animal-Classification/keys{/key_id}",
                      "collaborators_url":  "https://api.github.com/repos/AbhiGuru25/Animal-Classification/collaborators{/collaborator}",
                      "teams_url":  "https://api.github.com/repos/AbhiGuru25/Animal-Classification/teams",
                      "hooks_url":  "https://api.github.com/repos/AbhiGuru25/Animal-Classification/hooks",
                      "issue_events_url":  "https://api.github.com/repos/AbhiGuru25/Animal-Classification/issues/events{/number}",
                      "events_url":  "https://api.github.com/repos/AbhiGuru25/Animal-Classification/events",
                      "assignees_url":  "https://api.github.com/repos/AbhiGuru25/Animal-Classification/assignees{/user}",
                      "branches_url":  "https://api.github.com/repos/AbhiGuru25/Animal-Classification/branches{/branch}",
                      "tags_url":  "https://api.github.com/repos/AbhiGuru25/Animal-Classification/tags",
                      "blobs_url":  "https://api.github.com/repos/AbhiGuru25/Animal-Classification/git/blobs{/sha}",
                      "git_tags_url":  "https://api.github.com/repos/AbhiGuru25/Animal-Classification/git/tags{/sha}",
                      "git_refs_url":  "https://api.github.com/repos/AbhiGuru25/Animal-Classification/git/refs{/sha}",
                      "trees_url":  "https://api.github.com/repos/AbhiGuru25/Animal-Classification/git/trees{/sha}",
                      "statuses_url":  "https://api.github.com/repos/AbhiGuru25/Animal-Classification/statuses/{sha}",
                      "languages_url":  "https://api.github.com/repos/AbhiGuru25/Animal-Classification/languages",
                      "stargazers_url":  "https://api.github.com/repos/AbhiGuru25/Animal-Classification/stargazers",
                      "contributors_url":  "https://api.github.com/repos/AbhiGuru25/Animal-Classification/contributors",
                      "subscribers_url":  "https://api.github.com/repos/AbhiGuru25/Animal-Classification/subscribers",
                      "subscription_url":  "https://api.github.com/repos/AbhiGuru25/Animal-Classification/subscription",
                      "commits_url":  "https://api.github.com/repos/AbhiGuru25/Animal-Classification/commits{/sha}",
                      "git_commits_url":  "https://api.github.com/repos/AbhiGuru25/Animal-Classification/git/commits{/sha}",
                      "comments_url":  "https://api.github.com/repos/AbhiGuru25/Animal-Classification/comments{/number}",
                      "issue_comment_url":  "https://api.github.com/repos/AbhiGuru25/Animal-Classification/issues/comments{/number}",
                      "contents_url":  "https://api.github.com/repos/AbhiGuru25/Animal-Classification/contents/{+path}",
                      "compare_url":  "https://api.github.com/repos/AbhiGuru25/Animal-Classification/compare/{base}...{head}",
                      "merges_url":  "https://api.github.com/repos/AbhiGuru25/Animal-Classification/merges",
                      "archive_url":  "https://api.github.com/repos/AbhiGuru25/Animal-Classification/{archive_format}{/ref}",
                      "downloads_url":  "https://api.github.com/repos/AbhiGuru25/Animal-Classification/downloads",
                      "issues_url":  "https://api.github.com/repos/AbhiGuru25/Animal-Classification/issues{/number}",
                      "pulls_url":  "https://api.github.com/repos/AbhiGuru25/Animal-Classification/pulls{/number}",
                      "milestones_url":  "https://api.github.com/repos/AbhiGuru25/Animal-Classification/milestones{/number}",
                      "notifications_url":  "https://api.github.com/repos/AbhiGuru25/Animal-Classification/notifications{?since,all,participating}",
                      "labels_url":  "https://api.github.com/repos/AbhiGuru25/Animal-Classification/labels{/name}",
                      "releases_url":  "https://api.github.com/repos/AbhiGuru25/Animal-Classification/releases{/id}",
                      "deployments_url":  "https://api.github.com/repos/AbhiGuru25/Animal-Classification/deployments",
                      "created_at":  "2026-03-12T19:35:30Z",
                      "updated_at":  "2026-03-27T11:32:10Z",
                      "pushed_at":  "2026-03-27T11:32:05Z",
                      "git_url":  "git://github.com/AbhiGuru25/Animal-Classification.git",
                      "ssh_url":  "git@github.com:AbhiGuru25/Animal-Classification.git",
                      "clone_url":  "https://github.com/AbhiGuru25/Animal-Classification.git",
                      "svn_url":  "https://github.com/AbhiGuru25/Animal-Classification",
                      "homepage":  null,
                      "size":  36710,
                      "stargazers_count":  0,
                      "watchers_count":  0,
                      "language":  "Python",
                      "has_issues":  true,
                      "has_projects":  true,
                      "has_downloads":  true,
                      "has_wiki":  true,
                      "has_pages":  false,
                      "has_discussions":  false,
                      "forks_count":  0,
                      "mirror_url":  null,
                      "archived":  false,
                      "disabled":  false,
                      "open_issues_count":  0,
                      "license":  null,
                      "allow_forking":  true,
                      "is_template":  false,
                      "web_commit_signoff_required":  false,
                      "has_pull_requests":  true,
                      "pull_request_creation_policy":  "all",
                      "topics":  [

                                 ],
                      "visibility":  "public",
                      "forks":  0,
                      "open_issues":  0,
                      "watchers":  0,
                      "default_branch":  "main"
                  },
                  {
                      "id":  1149974024,
                      "node_id":  "R_kgDORIs2CA",
                      "name":  "splitora-mobile",
                      "full_name":  "AbhiGuru25/splitora-mobile",
                      "private":  false,
                      "owner":  {
                                    "login":  "AbhiGuru25",
                                    "id":  162453908,
                                    "node_id":  "U_kgDOCa7ZlA",
                                    "avatar_url":  "https://avatars.githubusercontent.com/u/162453908?v=4",
                                    "gravatar_id":  "",
                                    "url":  "https://api.github.com/users/AbhiGuru25",
                                    "html_url":  "https://github.com/AbhiGuru25",
                                    "followers_url":  "https://api.github.com/users/AbhiGuru25/followers",
                                    "following_url":  "https://api.github.com/users/AbhiGuru25/following{/other_user}",
                                    "gists_url":  "https://api.github.com/users/AbhiGuru25/gists{/gist_id}",
                                    "starred_url":  "https://api.github.com/users/AbhiGuru25/starred{/owner}{/repo}",
                                    "subscriptions_url":  "https://api.github.com/users/AbhiGuru25/subscriptions",
                                    "organizations_url":  "https://api.github.com/users/AbhiGuru25/orgs",
                                    "repos_url":  "https://api.github.com/users/AbhiGuru25/repos",
                                    "events_url":  "https://api.github.com/users/AbhiGuru25/events{/privacy}",
                                    "received_events_url":  "https://api.github.com/users/AbhiGuru25/received_events",
                                    "type":  "User",
                                    "user_view_type":  "public",
                                    "site_admin":  false
                                },
                      "html_url":  "https://github.com/AbhiGuru25/splitora-mobile",
                      "description":  "\"Modern expense splitting app with beautiful UI\"",
                      "fork":  false,
                      "url":  "https://api.github.com/repos/AbhiGuru25/splitora-mobile",
                      "forks_url":  "https://api.github.com/repos/AbhiGuru25/splitora-mobile/forks",
                      "keys_url":  "https://api.github.com/repos/AbhiGuru25/splitora-mobile/keys{/key_id}",
                      "collaborators_url":  "https://api.github.com/repos/AbhiGuru25/splitora-mobile/collaborators{/collaborator}",
                      "teams_url":  "https://api.github.com/repos/AbhiGuru25/splitora-mobile/teams",
                      "hooks_url":  "https://api.github.com/repos/AbhiGuru25/splitora-mobile/hooks",
                      "issue_events_url":  "https://api.github.com/repos/AbhiGuru25/splitora-mobile/issues/events{/number}",
                      "events_url":  "https://api.github.com/repos/AbhiGuru25/splitora-mobile/events",
                      "assignees_url":  "https://api.github.com/repos/AbhiGuru25/splitora-mobile/assignees{/user}",
                      "branches_url":  "https://api.github.com/repos/AbhiGuru25/splitora-mobile/branches{/branch}",
                      "tags_url":  "https://api.github.com/repos/AbhiGuru25/splitora-mobile/tags",
                      "blobs_url":  "https://api.github.com/repos/AbhiGuru25/splitora-mobile/git/blobs{/sha}",
                      "git_tags_url":  "https://api.github.com/repos/AbhiGuru25/splitora-mobile/git/tags{/sha}",
                      "git_refs_url":  "https://api.github.com/repos/AbhiGuru25/splitora-mobile/git/refs{/sha}",
                      "trees_url":  "https://api.github.com/repos/AbhiGuru25/splitora-mobile/git/trees{/sha}",
                      "statuses_url":  "https://api.github.com/repos/AbhiGuru25/splitora-mobile/statuses/{sha}",
                      "languages_url":  "https://api.github.com/repos/AbhiGuru25/splitora-mobile/languages",
                      "stargazers_url":  "https://api.github.com/repos/AbhiGuru25/splitora-mobile/stargazers",
                      "contributors_url":  "https://api.github.com/repos/AbhiGuru25/splitora-mobile/contributors",
                      "subscribers_url":  "https://api.github.com/repos/AbhiGuru25/splitora-mobile/subscribers",
                      "subscription_url":  "https://api.github.com/repos/AbhiGuru25/splitora-mobile/subscription",
                      "commits_url":  "https://api.github.com/repos/AbhiGuru25/splitora-mobile/commits{/sha}",
                      "git_commits_url":  "https://api.github.com/repos/AbhiGuru25/splitora-mobile/git/commits{/sha}",
                      "comments_url":  "https://api.github.com/repos/AbhiGuru25/splitora-mobile/comments{/number}",
                      "issue_comment_url":  "https://api.github.com/repos/AbhiGuru25/splitora-mobile/issues/comments{/number}",
                      "contents_url":  "https://api.github.com/repos/AbhiGuru25/splitora-mobile/contents/{+path}",
                      "compare_url":  "https://api.github.com/repos/AbhiGuru25/splitora-mobile/compare/{base}...{head}",
                      "merges_url":  "https://api.github.com/repos/AbhiGuru25/splitora-mobile/merges",
                      "archive_url":  "https://api.github.com/repos/AbhiGuru25/splitora-mobile/{archive_format}{/ref}",
                      "downloads_url":  "https://api.github.com/repos/AbhiGuru25/splitora-mobile/downloads",
                      "issues_url":  "https://api.github.com/repos/AbhiGuru25/splitora-mobile/issues{/number}",
                      "pulls_url":  "https://api.github.com/repos/AbhiGuru25/splitora-mobile/pulls{/number}",
                      "milestones_url":  "https://api.github.com/repos/AbhiGuru25/splitora-mobile/milestones{/number}",
                      "notifications_url":  "https://api.github.com/repos/AbhiGuru25/splitora-mobile/notifications{?since,all,participating}",
                      "labels_url":  "https://api.github.com/repos/AbhiGuru25/splitora-mobile/labels{/name}",
                      "releases_url":  "https://api.github.com/repos/AbhiGuru25/splitora-mobile/releases{/id}",
                      "deployments_url":  "https://api.github.com/repos/AbhiGuru25/splitora-mobile/deployments",
                      "created_at":  "2026-02-04T18:29:16Z",
                      "updated_at":  "2026-02-25T18:42:17Z",
                      "pushed_at":  "2026-02-25T18:42:13Z",
                      "git_url":  "git://github.com/AbhiGuru25/splitora-mobile.git",
                      "ssh_url":  "git@github.com:AbhiGuru25/splitora-mobile.git",
                      "clone_url":  "https://github.com/AbhiGuru25/splitora-mobile.git",
                      "svn_url":  "https://github.com/AbhiGuru25/splitora-mobile",
                      "homepage":  "https://splitora-mobile.vercel.app",
                      "size":  343,
                      "stargazers_count":  0,
                      "watchers_count":  0,
                      "language":  "TypeScript",
                      "has_issues":  true,
                      "has_projects":  true,
                      "has_downloads":  true,
                      "has_wiki":  true,
                      "has_pages":  false,
                      "has_discussions":  false,
                      "forks_count":  0,
                      "mirror_url":  null,
                      "archived":  false,
                      "disabled":  false,
                      "open_issues_count":  0,
                      "license":  null,
                      "allow_forking":  true,
                      "is_template":  false,
                      "web_commit_signoff_required":  false,
                      "has_pull_requests":  true,
                      "pull_request_creation_policy":  "all",
                      "topics":  [

                                 ],
                      "visibility":  "public",
                      "forks":  0,
                      "open_issues":  0,
                      "watchers":  0,
                      "default_branch":  "main"
                  },
                  {
                      "id":  1129864277,
                      "node_id":  "R_kgDOQ1hcVQ",
                      "name":  "ML-forecasting-project",
                      "full_name":  "AbhiGuru25/ML-forecasting-project",
                      "private":  false,
                      "owner":  {
                                    "login":  "AbhiGuru25",
                                    "id":  162453908,
                                    "node_id":  "U_kgDOCa7ZlA",
                                    "avatar_url":  "https://avatars.githubusercontent.com/u/162453908?v=4",
                                    "gravatar_id":  "",
                                    "url":  "https://api.github.com/users/AbhiGuru25",
                                    "html_url":  "https://github.com/AbhiGuru25",
                                    "followers_url":  "https://api.github.com/users/AbhiGuru25/followers",
                                    "following_url":  "https://api.github.com/users/AbhiGuru25/following{/other_user}",
                                    "gists_url":  "https://api.github.com/users/AbhiGuru25/gists{/gist_id}",
                                    "starred_url":  "https://api.github.com/users/AbhiGuru25/starred{/owner}{/repo}",
                                    "subscriptions_url":  "https://api.github.com/users/AbhiGuru25/subscriptions",
                                    "organizations_url":  "https://api.github.com/users/AbhiGuru25/orgs",
                                    "repos_url":  "https://api.github.com/users/AbhiGuru25/repos",
                                    "events_url":  "https://api.github.com/users/AbhiGuru25/events{/privacy}",
                                    "received_events_url":  "https://api.github.com/users/AbhiGuru25/received_events",
                                    "type":  "User",
                                    "user_view_type":  "public",
                                    "site_admin":  false
                                },
                      "html_url":  "https://github.com/AbhiGuru25/ML-forecasting-project",
                      "description":  "\"Time Series Forecasting for Patient Mobility using Prophet \u0026 EBM\"",
                      "fork":  false,
                      "url":  "https://api.github.com/repos/AbhiGuru25/ML-forecasting-project",
                      "forks_url":  "https://api.github.com/repos/AbhiGuru25/ML-forecasting-project/forks",
                      "keys_url":  "https://api.github.com/repos/AbhiGuru25/ML-forecasting-project/keys{/key_id}",
                      "collaborators_url":  "https://api.github.com/repos/AbhiGuru25/ML-forecasting-project/collaborators{/collaborator}",
                      "teams_url":  "https://api.github.com/repos/AbhiGuru25/ML-forecasting-project/teams",
                      "hooks_url":  "https://api.github.com/repos/AbhiGuru25/ML-forecasting-project/hooks",
                      "issue_events_url":  "https://api.github.com/repos/AbhiGuru25/ML-forecasting-project/issues/events{/number}",
                      "events_url":  "https://api.github.com/repos/AbhiGuru25/ML-forecasting-project/events",
                      "assignees_url":  "https://api.github.com/repos/AbhiGuru25/ML-forecasting-project/assignees{/user}",
                      "branches_url":  "https://api.github.com/repos/AbhiGuru25/ML-forecasting-project/branches{/branch}",
                      "tags_url":  "https://api.github.com/repos/AbhiGuru25/ML-forecasting-project/tags",
                      "blobs_url":  "https://api.github.com/repos/AbhiGuru25/ML-forecasting-project/git/blobs{/sha}",
                      "git_tags_url":  "https://api.github.com/repos/AbhiGuru25/ML-forecasting-project/git/tags{/sha}",
                      "git_refs_url":  "https://api.github.com/repos/AbhiGuru25/ML-forecasting-project/git/refs{/sha}",
                      "trees_url":  "https://api.github.com/repos/AbhiGuru25/ML-forecasting-project/git/trees{/sha}",
                      "statuses_url":  "https://api.github.com/repos/AbhiGuru25/ML-forecasting-project/statuses/{sha}",
                      "languages_url":  "https://api.github.com/repos/AbhiGuru25/ML-forecasting-project/languages",
                      "stargazers_url":  "https://api.github.com/repos/AbhiGuru25/ML-forecasting-project/stargazers",
                      "contributors_url":  "https://api.github.com/repos/AbhiGuru25/ML-forecasting-project/contributors",
                      "subscribers_url":  "https://api.github.com/repos/AbhiGuru25/ML-forecasting-project/subscribers",
                      "subscription_url":  "https://api.github.com/repos/AbhiGuru25/ML-forecasting-project/subscription",
                      "commits_url":  "https://api.github.com/repos/AbhiGuru25/ML-forecasting-project/commits{/sha}",
                      "git_commits_url":  "https://api.github.com/repos/AbhiGuru25/ML-forecasting-project/git/commits{/sha}",
                      "comments_url":  "https://api.github.com/repos/AbhiGuru25/ML-forecasting-project/comments{/number}",
                      "issue_comment_url":  "https://api.github.com/repos/AbhiGuru25/ML-forecasting-project/issues/comments{/number}",
                      "contents_url":  "https://api.github.com/repos/AbhiGuru25/ML-forecasting-project/contents/{+path}",
                      "compare_url":  "https://api.github.com/repos/AbhiGuru25/ML-forecasting-project/compare/{base}...{head}",
                      "merges_url":  "https://api.github.com/repos/AbhiGuru25/ML-forecasting-project/merges",
                      "archive_url":  "https://api.github.com/repos/AbhiGuru25/ML-forecasting-project/{archive_format}{/ref}",
                      "downloads_url":  "https://api.github.com/repos/AbhiGuru25/ML-forecasting-project/downloads",
                      "issues_url":  "https://api.github.com/repos/AbhiGuru25/ML-forecasting-project/issues{/number}",
                      "pulls_url":  "https://api.github.com/repos/AbhiGuru25/ML-forecasting-project/pulls{/number}",
                      "milestones_url":  "https://api.github.com/repos/AbhiGuru25/ML-forecasting-project/milestones{/number}",
                      "notifications_url":  "https://api.github.com/repos/AbhiGuru25/ML-forecasting-project/notifications{?since,all,participating}",
                      "labels_url":  "https://api.github.com/repos/AbhiGuru25/ML-forecasting-project/labels{/name}",
                      "releases_url":  "https://api.github.com/repos/AbhiGuru25/ML-forecasting-project/releases{/id}",
                      "deployments_url":  "https://api.github.com/repos/AbhiGuru25/ML-forecasting-project/deployments",
                      "created_at":  "2026-01-07T17:35:08Z",
                      "updated_at":  "2026-01-07T18:32:59Z",
                      "pushed_at":  "2026-01-07T18:32:54Z",
                      "git_url":  "git://github.com/AbhiGuru25/ML-forecasting-project.git",
                      "ssh_url":  "git@github.com:AbhiGuru25/ML-forecasting-project.git",
                      "clone_url":  "https://github.com/AbhiGuru25/ML-forecasting-project.git",
                      "svn_url":  "https://github.com/AbhiGuru25/ML-forecasting-project",
                      "homepage":  null,
                      "size":  6430,
                      "stargazers_count":  0,
                      "watchers_count":  0,
                      "language":  "Python",
                      "has_issues":  true,
                      "has_projects":  true,
                      "has_downloads":  true,
                      "has_wiki":  true,
                      "has_pages":  false,
                      "has_discussions":  false,
                      "forks_count":  0,
                      "mirror_url":  null,
                      "archived":  false,
                      "disabled":  false,
                      "open_issues_count":  0,
                      "license":  null,
                      "allow_forking":  true,
                      "is_template":  false,
                      "web_commit_signoff_required":  false,
                      "has_pull_requests":  true,
                      "pull_request_creation_policy":  "all",
                      "topics":  [

                                 ],
                      "visibility":  "public",
                      "forks":  0,
                      "open_issues":  0,
                      "watchers":  0,
                      "default_branch":  "main"
                  },
                  {
                      "id":  1088945776,
                      "node_id":  "R_kgDOQOf-cA",
                      "name":  "Detecting-FRAUD-transactions-of-ETHEREUM",
                      "full_name":  "AbhiGuru25/Detecting-FRAUD-transactions-of-ETHEREUM",
                      "private":  false,
                      "owner":  {
                                    "login":  "AbhiGuru25",
                                    "id":  162453908,
                                    "node_id":  "U_kgDOCa7ZlA",
                                    "avatar_url":  "https://avatars.githubusercontent.com/u/162453908?v=4",
                                    "gravatar_id":  "",
                                    "url":  "https://api.github.com/users/AbhiGuru25",
                                    "html_url":  "https://github.com/AbhiGuru25",
                                    "followers_url":  "https://api.github.com/users/AbhiGuru25/followers",
                                    "following_url":  "https://api.github.com/users/AbhiGuru25/following{/other_user}",
                                    "gists_url":  "https://api.github.com/users/AbhiGuru25/gists{/gist_id}",
                                    "starred_url":  "https://api.github.com/users/AbhiGuru25/starred{/owner}{/repo}",
                                    "subscriptions_url":  "https://api.github.com/users/AbhiGuru25/subscriptions",
                                    "organizations_url":  "https://api.github.com/users/AbhiGuru25/orgs",
                                    "repos_url":  "https://api.github.com/users/AbhiGuru25/repos",
                                    "events_url":  "https://api.github.com/users/AbhiGuru25/events{/privacy}",
                                    "received_events_url":  "https://api.github.com/users/AbhiGuru25/received_events",
                                    "type":  "User",
                                    "user_view_type":  "public",
                                    "site_admin":  false
                                },
                      "html_url":  "https://github.com/AbhiGuru25/Detecting-FRAUD-transactions-of-ETHEREUM",
                      "description":  null,
                      "fork":  false,
                      "url":  "https://api.github.com/repos/AbhiGuru25/Detecting-FRAUD-transactions-of-ETHEREUM",
                      "forks_url":  "https://api.github.com/repos/AbhiGuru25/Detecting-FRAUD-transactions-of-ETHEREUM/forks",
                      "keys_url":  "https://api.github.com/repos/AbhiGuru25/Detecting-FRAUD-transactions-of-ETHEREUM/keys{/key_id}",
                      "collaborators_url":  "https://api.github.com/repos/AbhiGuru25/Detecting-FRAUD-transactions-of-ETHEREUM/collaborators{/collaborator}",
                      "teams_url":  "https://api.github.com/repos/AbhiGuru25/Detecting-FRAUD-transactions-of-ETHEREUM/teams",
                      "hooks_url":  "https://api.github.com/repos/AbhiGuru25/Detecting-FRAUD-transactions-of-ETHEREUM/hooks",
                      "issue_events_url":  "https://api.github.com/repos/AbhiGuru25/Detecting-FRAUD-transactions-of-ETHEREUM/issues/events{/number}",
                      "events_url":  "https://api.github.com/repos/AbhiGuru25/Detecting-FRAUD-transactions-of-ETHEREUM/events",
                      "assignees_url":  "https://api.github.com/repos/AbhiGuru25/Detecting-FRAUD-transactions-of-ETHEREUM/assignees{/user}",
                      "branches_url":  "https://api.github.com/repos/AbhiGuru25/Detecting-FRAUD-transactions-of-ETHEREUM/branches{/branch}",
                      "tags_url":  "https://api.github.com/repos/AbhiGuru25/Detecting-FRAUD-transactions-of-ETHEREUM/tags",
                      "blobs_url":  "https://api.github.com/repos/AbhiGuru25/Detecting-FRAUD-transactions-of-ETHEREUM/git/blobs{/sha}",
                      "git_tags_url":  "https://api.github.com/repos/AbhiGuru25/Detecting-FRAUD-transactions-of-ETHEREUM/git/tags{/sha}",
                      "git_refs_url":  "https://api.github.com/repos/AbhiGuru25/Detecting-FRAUD-transactions-of-ETHEREUM/git/refs{/sha}",
                      "trees_url":  "https://api.github.com/repos/AbhiGuru25/Detecting-FRAUD-transactions-of-ETHEREUM/git/trees{/sha}",
                      "statuses_url":  "https://api.github.com/repos/AbhiGuru25/Detecting-FRAUD-transactions-of-ETHEREUM/statuses/{sha}",
                      "languages_url":  "https://api.github.com/repos/AbhiGuru25/Detecting-FRAUD-transactions-of-ETHEREUM/languages",
                      "stargazers_url":  "https://api.github.com/repos/AbhiGuru25/Detecting-FRAUD-transactions-of-ETHEREUM/stargazers",
                      "contributors_url":  "https://api.github.com/repos/AbhiGuru25/Detecting-FRAUD-transactions-of-ETHEREUM/contributors",
                      "subscribers_url":  "https://api.github.com/repos/AbhiGuru25/Detecting-FRAUD-transactions-of-ETHEREUM/subscribers",
                      "subscription_url":  "https://api.github.com/repos/AbhiGuru25/Detecting-FRAUD-transactions-of-ETHEREUM/subscription",
                      "commits_url":  "https://api.github.com/repos/AbhiGuru25/Detecting-FRAUD-transactions-of-ETHEREUM/commits{/sha}",
                      "git_commits_url":  "https://api.github.com/repos/AbhiGuru25/Detecting-FRAUD-transactions-of-ETHEREUM/git/commits{/sha}",
                      "comments_url":  "https://api.github.com/repos/AbhiGuru25/Detecting-FRAUD-transactions-of-ETHEREUM/comments{/number}",
                      "issue_comment_url":  "https://api.github.com/repos/AbhiGuru25/Detecting-FRAUD-transactions-of-ETHEREUM/issues/comments{/number}",
                      "contents_url":  "https://api.github.com/repos/AbhiGuru25/Detecting-FRAUD-transactions-of-ETHEREUM/contents/{+path}",
                      "compare_url":  "https://api.github.com/repos/AbhiGuru25/Detecting-FRAUD-transactions-of-ETHEREUM/compare/{base}...{head}",
                      "merges_url":  "https://api.github.com/repos/AbhiGuru25/Detecting-FRAUD-transactions-of-ETHEREUM/merges",
                      "archive_url":  "https://api.github.com/repos/AbhiGuru25/Detecting-FRAUD-transactions-of-ETHEREUM/{archive_format}{/ref}",
                      "downloads_url":  "https://api.github.com/repos/AbhiGuru25/Detecting-FRAUD-transactions-of-ETHEREUM/downloads",
                      "issues_url":  "https://api.github.com/repos/AbhiGuru25/Detecting-FRAUD-transactions-of-ETHEREUM/issues{/number}",
                      "pulls_url":  "https://api.github.com/repos/AbhiGuru25/Detecting-FRAUD-transactions-of-ETHEREUM/pulls{/number}",
                      "milestones_url":  "https://api.github.com/repos/AbhiGuru25/Detecting-FRAUD-transactions-of-ETHEREUM/milestones{/number}",
                      "notifications_url":  "https://api.github.com/repos/AbhiGuru25/Detecting-FRAUD-transactions-of-ETHEREUM/notifications{?since,all,participating}",
                      "labels_url":  "https://api.github.com/repos/AbhiGuru25/Detecting-FRAUD-transactions-of-ETHEREUM/labels{/name}",
                      "releases_url":  "https://api.github.com/repos/AbhiGuru25/Detecting-FRAUD-transactions-of-ETHEREUM/releases{/id}",
                      "deployments_url":  "https://api.github.com/repos/AbhiGuru25/Detecting-FRAUD-transactions-of-ETHEREUM/deployments",
                      "created_at":  "2025-11-03T17:11:24Z",
                      "updated_at":  "2026-01-02T12:18:55Z",
                      "pushed_at":  "2026-01-02T12:18:52Z",
                      "git_url":  "git://github.com/AbhiGuru25/Detecting-FRAUD-transactions-of-ETHEREUM.git",
                      "ssh_url":  "git@github.com:AbhiGuru25/Detecting-FRAUD-transactions-of-ETHEREUM.git",
                      "clone_url":  "https://github.com/AbhiGuru25/Detecting-FRAUD-transactions-of-ETHEREUM.git",
                      "svn_url":  "https://github.com/AbhiGuru25/Detecting-FRAUD-transactions-of-ETHEREUM",
                      "homepage":  null,
                      "size":  991,
                      "stargazers_count":  0,
                      "watchers_count":  0,
                      "language":  "HTML",
                      "has_issues":  true,
                      "has_projects":  true,
                      "has_downloads":  true,
                      "has_wiki":  true,
                      "has_pages":  false,
                      "has_discussions":  false,
                      "forks_count":  0,
                      "mirror_url":  null,
                      "archived":  false,
                      "disabled":  false,
                      "open_issues_count":  0,
                      "license":  null,
                      "allow_forking":  true,
                      "is_template":  false,
                      "web_commit_signoff_required":  false,
                      "has_pull_requests":  true,
                      "pull_request_creation_policy":  "all",
                      "topics":  [

                                 ],
                      "visibility":  "public",
                      "forks":  0,
                      "open_issues":  0,
                      "watchers":  0,
                      "default_branch":  "main"
                  }
              ],
    "Count":  10
}
